{
	"configurations" : 
	[
		{
			"directories" : 
			[
				{
					"build" : ".",
					"jsonFile" : "directory-.-Debug-f5ebdc15457944623624.json",
					"minimumCMakeVersion" : 
					{
						"string" : "3.6.0"
					},
					"projectIndex" : 0,
					"source" : "."
				}
			],
			"name" : "Debug",
			"projects" : 
			[
				{
					"directoryIndexes" : 
					[
						0
					],
					"name" : "Project"
				}
			],
			"targets" : []
		}
	],
	"kind" : "codemodel",
	"paths" : 
	{
		"build" : "/Users/mac_mini/Desktop/\u9879\u76ee/\u9b54\u6837\u80a1\u4efd/flutter-watch-sdk/moyoung_ble_plugin/example/android/app/.cxx/Debug/173m5w1s/arm64-v8a",
		"source" : "/Users/mac_mini/Documents/flutter/packages/flutter_tools/gradle/src/main/groovy"
	},
	"version" : 
	{
		"major" : 2,
		"minor" : 3
	}
}
